pyexec_shell/__init__.py
pyexec_shell/exec_shell.py
pyexec_shell-1.0.5.dist-info/LICENSE
pyexec_shell-1.0.5.dist-info/METADATA
pyexec_shell-1.0.5.dist-info/WHEEL
pyexec_shell-1.0.5.dist-info/top_level.txt
pyexec_shell-1.0.5.dist-info/zip-safe
pyexec_shell-1.0.5.dist-info/RECORD
