Metadata-Version: 2.1
Name: pyexec_shell
Version: 1.0.5
Summary: shell助手
Home-page: https://github.com/buyfakett
Author: buyfakett
Author-email: buyfakett@vip.qq.com
License: MIT
Requires-Python: >=3.6
License-File: LICENSE
